<?xml version='1.0' encoding='UTF-8'?>
<!DOCTYPE Workflow PUBLIC "sailpoint.dtd" "sailpoint.dtd">
<Workflow handler="sailpoint.api.StandardWorkflowHandler" libraries="Identity,BatchRequest" name="Ascension-Workflow-Bulk-CreateContractor" taskType="LCM" type="LCMRegistration">
  <Variable input="true" name="userInformationMap"/>
  <Variable initializer="false" name="trace">
    <Description>Used for debugging this workflow and when set to true trace
      will be sent to stdout.</Description>
  </Variable>
  <Variable name="identityID"/>
  <Variable initializer="true" name="transient"/>
  <Variable initializer="false" name="enableAccounts"/>
  <Variable input="true" name="identityName">
    <Description>The name of the identity being updated.</Description>
  </Variable>
  <Variable initializer="false" name="userExists">
    <Description>whether user already exists for re-enablement.</Description>
  </Variable>
  <Variable name="matchingUsers">
    <Description>list of users matching for re-enablement.</Description>
    <Script>
      <Source><![CDATA[
      	return (new ArrayList());
      ]]></Source>
    </Script>
  </Variable>
  <Variable name="identityModel">
    <Description>The custom model that is used to house and pass application data.</Description>
  </Variable>
  <Variable initializer="script:(identityDisplayName != void) ? identityDisplayName : resolveDisplayName(identityName)" input="true" name="identityDisplayName">
    <Description>The displayName of the identity being updated.
      Query for this using a projection query and fall back to the name.</Description>
  </Variable>
  <Variable name="launcher">
    <Description>requester of the form</Description>
    <Script>
      <Source><![CDATA[
      return context.getUserName();
      ]]></Source>
    </Script>
  </Variable>
  <Variable name="plan">
    <Description>The provisioning plan, which is built by a service method.</Description>
  </Variable>
  <Variable name="planAD">
    <Description>The provisioning plan, which is built by a service method.</Description>
  </Variable>
  <Variable editable="true" initializer="false" name="optimisticProvisioning">
    <Description>Set to true to enable optimistic provisioning.  This will cause
      changes to the entitlements compiled from role assignments to be 
      applied immediately to the identity cube rather than waiting
      for the next refresh/reaggregation after the provisioning system
      completes the request.</Description>
  </Variable>
  <Variable editable="true" initializer="true" name="backgroundProvisioning"/>
  <Variable editable="true" initializer="false" name="foregroundProvisioning">
    <Description>Normally provisioning is done in a step that uses the &amp;quot;background&amp;quot;
      option to force the workflow to be suspend and be resumed in ah
      background task thread.  This prevents the browser session from
      hanging since provision can sometimes take a long time.  For demos
      and testing it can be better to do this in the foreground so that
      provisioning will have been performed when control is returned to the
      user.  This prevents having to run the Perform Maintenance task to 
      see the results of the request.</Description>
  </Variable>
  <Variable initializer="IDM Team" input="true" name="fallbackApprover">
    <Description>A String that specifies the name of the Identity that will 
      be assigned any approvals where the owner of the approver 
      can&amp;#39;t be resolved. Example if the scheme is &amp;quot;owner&amp;quot; and the 
      application doesn&amp;#39;t specify and owner.</Description>
  </Variable>
  <Variable initializer="LCM" input="true" name="source">
    <Description>String version of sailpoint.object.Source to indicate
      where the request originated.  Defaults to LCM.</Description>
  </Variable>
  <Variable initializer="false" name="trace">
    <Description>Used for debugging this workflow and when set to true trace
      will be sent to stdout.</Description>
  </Variable>
  <Variable name="project">
    <Description>ProvisioningProject which is just a compiled version of the ProvisioningPlan.</Description>
  </Variable>
  <Variable name="identityRequestId" output="true">
    <Description>The sequence id of the Identity request object which is stored in 
      the name field of the identity request.</Description>
  </Variable>
  <Variable name="iiqIdentityRequestId" output="true">
    <Description>
      The sequence id of the Identity request object which is stored in 
      the name field of the identity request.
    </Description>
  </Variable>
  <Variable name="cart" output="true">
    <Description>This variable includes all ApprovalItems that are part of 
      the request process and is updated during the AfterScript
      of the approval process by assimilating the decisions 
      and comments from the Approvals copy of the ApprovalItem.</Description>
  </Variable>
  <Variable initializer="Normal" input="true" name="workItemPriority">
    <Description>The String version of a WorkItem.Priority. This variable is 
      used to set the priority on all of the workitems generated 
      as part of this workflow and also set on the IdentityRequest
      object.</Description>
  </Variable>
  <Variable name="policyViolations">
    <Description>
         List of policy violations that were found during our initial policy scan.
         This list is passed into each work item so the approvers can see
         pending violations.
      </Description>
  </Variable>
  <Variable initializer="Bulk Create Contractor Identity" name="flow"/>
  <Variable editable="true" initializer="true" name="doRefresh">
    <Description>
      Set to true to cause an identity refresh after the changes in the plan
      have been provisioned.  This is normally off, you might want this on
      if you want modification of identity or link attributes to result in
      an immediate re-evaluation of assigned and detected roles.
    </Description>
  </Variable>
  <Variable name="partialMatchingUsers">
    <Description>list of users matching for re-enablement.</Description>
    <Script>
      <Source><![CDATA[
      	return (new ArrayList());
      ]]></Source>
    </Script>
  </Variable>
  <RuleLibraries>
    <Reference class="sailpoint.object.Rule" name="Ascension-Rule-Library"/>
    <Reference class="sailpoint.object.Rule" name="Ascension-RuleLibrary-Encryption"/>
    <Reference class="sailpoint.object.Rule" name="Rule-Ascension-ExistingAccount-RuleLibrary"/>
    <Reference class="sailpoint.object.Rule" name="Rule-Ascension-EmailAddress-RuleLibrary"/>
    <Reference class="sailpoint.object.Rule" name="Rule-GSuite-AccessToken"/>
    <Reference class="sailpoint.object.Rule" name="Ascension-Rule-Library-DatabaseFields"/>
    <Reference class="sailpoint.object.Rule" name="Ascension-Rule-InitialName-Sequence-Generator"/>
    <Reference class="sailpoint.object.Rule" name="Ascension-Rule-Persona-Management-RuleLibrary"/>
  </RuleLibraries>
  <Step icon="Start" name="Start" posX="28" posY="10">
    <Transition to="Initialize"/>
  </Step>
  <Step action="call:getIdentityModel" name="Initialize" posX="98" posY="10" resultVariable="identityModel">
    <Description>
      Initialize the data for the identity that we are creating.
    </Description>
    <Transition to="Contractor Search Form"/>
  </Step>
  <Step icon="Default" name="Contractor Search Form" posX="208" posY="10" resultVariable="identityModel">
    <Description>
      Display the Search Contractor form
    </Description>
    <Script>
      <Source><![CDATA[
     if (userInformationMap != null && !userInformationMap.isEmpty()) {
    	 identityModel.putAll(userInformationMap);
    }
    return identityModel;
     ]]></Source>
    </Script>
    <Transition to="Check Existing User"/>
  </Step>
  <Step name="Check Existing User" posX="802" posY="10" resultVariable="matchingUsers">
    <Description>
      Set the identityName workflow variable based on the form input.
    </Description>
    <Script>
      <Source><![CDATA[
        import java.text.SimpleDateFormat;  
	      import sailpoint.object.Custom;
        import sailpoint.object.Filter;
        import sailpoint.tools.Util;
        import sailpoint.object.Link;
        import sailpoint.object.QueryOptions;
        
        Custom custom = context.getObjectByName(Custom.class, "Ascension-Custom-ContractorConfiguration");
        List contractorTypes = new ArrayList();
        
       
        if(custom!=null && custom.get("ContractorType") !=null){
        	contractorTypes = custom.get("ContractorType");
        	//comment decache //context.decache(custom);
        }
        Filter empTypeFilter = Filter.in("type", contractorTypes);
        Filter inactiveFilter = Filter.eq("inactive", true);
       	Filter lastnameFilter = Filter.eq("lastname", identityModel.get("lastname"));
        Filter firstnameFilter = Filter.eq("firstname", identityModel.get("firstname"));
        
        Filter ssnFinalFilter = Filter.eq("ssn", identityModel.get("ssn"));
        if(decryptAES(identityModel.get("ssn")) != null){
         	ssnFinalFilter = Filter.or(ssnFinalFilter ,Filter.eq("ssn", decryptAES(identityModel.get("ssn"))));
        }
        else{
          ssnFinalFilter = Filter.or(ssnFinalFilter ,Filter.eq("ssn", encryptAES(identityModel.get("ssn"))));
        }
        

        Filter dobFinalFilter = Filter.eq("dob", identityModel.get("dob"));
        
        if(decryptAES(identityModel.get("dob")) != null){
         	dobFinalFilter = Filter.or(dobFinalFilter ,Filter.eq("dob", decryptAES(identityModel.get("dob"))));
        }
        else{
          dobFinalFilter = Filter.or(dobFinalFilter ,Filter.eq("dob", encryptAES(identityModel.get("dob"))));
        }
        
        Filter endFilter = Filter.and(empTypeFilter, lastnameFilter, firstnameFilter,ssnFinalFilter, dobFinalFilter);
              
        QueryOptions qo = new QueryOptions();
        qo.add(endFilter);
        
        List properties = new ArrayList();
        properties.add("name");
        Iterator iter = context.search(Identity.class, qo, properties);
        
        while(iter.hasNext()) {
        	Object[] currentUser = iter.next();
        
        if(currentUser != null && currentUser.length > 0 && currentUser[0] != null) {
        			matchingUsers.add(currentUser[0]);  
        		}        
        }
        
        if(null != iter){
       		Util.flushIterator(iter);
        }
        
        
        if(null != matchingUsers && !matchingUsers.isEmpty() && matchingUsers.size() == 1){
        	//Setting identityName to partialFormUser - to be used in Clean IdentityModel and Set IdentityName
          identityModel.put("partialFormUser", matchingUsers.get(0));
        }
  
				return matchingUsers;
        
      ]]></Source>
    </Script>
    <Transition to="Check Partial Match User" when="script:(null != matchingUsers &amp;&amp;  matchingUsers.isEmpty())"/>
    <Transition to="Partial Match Form" when="script:(null != matchingUsers &amp;&amp;  !matchingUsers.isEmpty() &amp;&amp; matchingUsers.size() &gt; 1 )"/>
    <Transition to="Clean IdentityModel and Set IdentityName" when="script:(null != matchingUsers &amp;&amp;  !matchingUsers.isEmpty() &amp;&amp; matchingUsers.size() == 1)"/>
  </Step>
  <Step name="Check Partial Match User" posX="802" posY="10" resultVariable="partialMatchingUsers">
    <Arg name="identityModel" value="ref:identityModel"/>
    <Description>
      check the partial search based on the form input.
    </Description>
    <Script>
      <Source><![CDATA[
       import java.text.SimpleDateFormat;  
        import sailpoint.object.Custom;
        import sailpoint.object.Filter;
        import sailpoint.tools.Util;
        import sailpoint.object.Link;
        import sailpoint.object.QueryOptions;

        Custom custom = context.getObjectByName(Custom.class, "Ascension-Custom-ContractorConfiguration");
        List userTypes = new ArrayList();   

        List orderLists = new ArrayList();

        if(custom!=null && custom.get("userTypes") !=null){
        userTypes = custom.get("userTypes");
        //comment decache //context.decache(custom);
        }

        Filter empTypeFilter = Filter.in("type", userTypes);
        Filter lastnameFilter = Filter.eq("lastname", identityModel.get("lastname"));
        Filter firstnameFilter = Filter.eq("firstname", identityModel.get("firstname"));

        Filter ssnFinalFilter = Filter.eq("ssn", identityModel.get("ssn"));
        if(decryptAES(identityModel.get("ssn")) != null){
        ssnFinalFilter = Filter.or(ssnFinalFilter ,Filter.eq("ssn", decryptAES(identityModel.get("ssn"))));
        }
        else{
        ssnFinalFilter = Filter.or(ssnFinalFilter ,Filter.eq("ssn", encryptAES(identityModel.get("ssn"))));
        }


        Filter dobFinalFilter = Filter.eq("dob", identityModel.get("dob"));

        if(decryptAES(identityModel.get("dob")) != null){
        dobFinalFilter = Filter.or(dobFinalFilter ,Filter.eq("dob", decryptAES(identityModel.get("dob"))));
        }
        else{
        dobFinalFilter = Filter.or(dobFinalFilter ,Filter.eq("dob", encryptAES(identityModel.get("dob"))));
        }

        orderLists.add("lastname,ssn,dob");
        orderLists.add("firstname,ssn,dob");
        orderLists.add("lastname,firstname,dob");
        orderLists.add("lastname,ssn,firstname");
        
				List properties = new ArrayList();
        properties.add("name");
				properties.add("displayName");
        properties.add("internalId");

        for(Object orderList : orderLists){    

        StringTokenizer st = new StringTokenizer(orderList,","); 
        Filter finalFilter = empTypeFilter;
        while (st.hasMoreTokens()) { 

        String filterName = st.nextToken();
        if(Util.nullSafeCaseInsensitiveEq("lastname",filterName)){
        finalFilter = finalFilter.and(finalFilter,lastnameFilter);
        }
        else if(Util.nullSafeCaseInsensitiveEq("firstname",filterName)){ 
        finalFilter = finalFilter.and(finalFilter,firstnameFilter);      
        }
        else if(Util.nullSafeCaseInsensitiveEq("ssn",filterName)){
        finalFilter = finalFilter.and(finalFilter,ssnFinalFilter);
        }
        else if(Util.nullSafeCaseInsensitiveEq("dob",filterName)){
        finalFilter = finalFilter.and(finalFilter,dobFinalFilter);
        }             
        }

        QueryOptions qo = new QueryOptions();
        qo.addFilter(finalFilter);    
        

        Iterator iter = context.search(Identity.class, qo, properties);

        while(iter.hasNext()) {
        Object[] currentUser = iter.next();       	
        if(currentUser != null && currentUser[0] != null && currentUser[1] != null && currentUser[2] != null) {
        
        String userString = currentUser[0] +","+currentUser[1]+","+currentUser[2];
       
        partialMatchingUsers.add(userString); 
        }
        }
        
        if(null != iter){
        Util.flushIterator(iter);
        }
        if(null != partialMatchingUsers && !partialMatchingUsers.isEmpty()){       
        break;
        }
        else{
        continue;
        }	
        }  
        
        if(null != partialMatchingUsers && partialMatchingUsers.isEmpty()){
        
        Filter lastnameTransposeFilter = Filter.eq("lastname", identityModel.get("firstname"));
        Filter firstnameTransposeFilter = Filter.eq("firstname", identityModel.get("lastname"));
        
        QueryOptions qoFinal = new QueryOptions();
        qoFinal.add(empTypeFilter, firstnameTransposeFilter, lastnameTransposeFilter, ssnFinalFilter, dobFinalFilter);

        Iterator iterFinal = context.search(Identity.class, qoFinal, properties);

        while(iterFinal.hasNext()) {
        Object[] currentUser = iterFinal.next();       	
        if(currentUser != null && currentUser[0] != null && currentUser[1] != null && currentUser[2] != null) {
        
        String userString = currentUser[0] +","+currentUser[1]+","+currentUser[2];
       
        partialMatchingUsers.add(userString); 
        }
        }
        
        if(null != iterFinal){
        Util.flushIterator(iterFinal);
        }
        }
        
        
         if ( identityModel != null && identityModel.get("dbFields") != null) {
        	identityModel.remove("dbFields");
        }
   

        return partialMatchingUsers;       
      ]]></Source>
    </Script>
    <Transition to="Notification For Administrator" when="script:(null != partialMatchingUsers &amp;&amp;  !partialMatchingUsers.isEmpty())"/>
    <Transition to="Set Identity Name"/>
  </Step>
  <Step icon="Notification" name="Notification For Administrator" posX="1160" posY="242">
    <Script>
      <Source><![CDATA[
        import sailpoint.object.Identity;
        import sailpoint.object.EmailOptions;
        import sailpoint.object.EmailTemplate;
        import sailpoint.api.ObjectUtil;

        EmailTemplate template = context.getObjectByName(EmailTemplate.class, "Ascension-EmailTemplate-PartialMatch-Approver");
				
        Identity workgroupID = context.getObjectByName(Identity.class,"PartialMatchContractors");
        List emailRecipientAddresses = ObjectUtil.getEffectiveEmails(context, workgroupID);
        
        Map args = new HashMap();
        
        args.put("identityDisplayName",identityDisplayName);
        args.put("launcher",launcher);
        args.put("identityName",identityName);

        EmailOptions options = new EmailOptions(emailRecipientAddresses, args);

        if(null != options && template !=null){
          context.sendEmailNotification(template,options);
          //comment decache //context.decache(template);
        }
  		]]></Source>
    </Script>
    <Transition to="Partial Match Form"/>
  </Step>
  <Step icon="AdminWorkitem" name="Partial Match Form" posX="208" posY="10">
    <Approval mode="serial" owner="PartialMatchContractors" return="identityModel" send="partialMatchingUsers,matchingUsers">
      <Arg name="workItemType" value="Form"/>
      <Arg name="workItemDescription" value="Partial Match Contractor"/>
      <Arg name="workItemForm" value="Ascension-Form-PartialMatchForm"/>
      <Arg name="workItemFormBasePath" value="identityModel"/>
    </Approval>
    <Description>
      Generate the Partial match form and assign to administrator
    </Description>
    <Transition to="Clean IdentityModel and Set IdentityName" when="script:(approved &amp;&amp; null != identityModel &amp;&amp; null != identityModel.get(&quot;partialFormUser&quot;))"/>
    <Transition to="Set Identity Name"/>
  </Step>
  <Step name="Set Identity Name" posX="984" posY="10" resultVariable="identityName">
    <Arg name="identityModel" value="ref:identityModel"/>
    <Description>
      Set the identityName workflow variable based on the form input.
    </Description>
    <Script>
      <Source><![CDATA[
        import java.text.SimpleDateFormat;  

        String name = "";
        String encryptDOB ="";
        String encryptSSN = "";
        String locationID = "";
        String depID = "";
        String businessID ="";
        String locationName = "";
        String depNum = "";
        
        if(null != identityModel){
          if(null != identityModel.get("firstname") && null != identityModel.get("lastname")){
        		name = initialUserName();
            identityModel.put("name",name);
          }

          if(null != identityModel.get("dob" ) && !Util.nullSafeCaseInsensitiveEq(identityModel.get("domain"),"amita")){
            encryptDOB = encryptAES(identityModel.get("dob"));       
            identityModel.put("dob",encryptDOB);
          }
          if(null != identityModel.get("ssn") && !Util.nullSafeCaseInsensitiveEq(identityModel.get("domain"),"amita")){
            encryptSSN = encryptAES(identityModel.get("ssn"));       
            identityModel.put("ssn",encryptSSN);
          }
        	if(null != identityModel.get("isContractorManager")){
        		if(identityModel.get("isContractorManager")){
        			identityModel.put("isContractorManager","true");
        		}
        		else{
        			identityModel.put("isContractorManager","false");
        		}                
          }
        	if(Util.nullSafeCaseInsensitiveEq(identityModel.get("domain"),"amita")){
            if(Util.isNotNullOrEmpty(identityModel.get("buildingId"))){
              locationName = identityModel.get("buildingId");       
              identityModel.put("location",getLocationName(locationName));
        			identityModel.put("locationDescription",getLocationName(locationName));
            }
            if(Util.isNotNullOrEmpty(identityModel.get("departmentNumber"))){
              depNum = identityModel.get("departmentNumber");       
              identityModel.put("department",getDepartmentName(depNum));
            }
        		if(Util.isNotNullOrEmpty(identityModel.get("buildingId")) && Util.isNotNullOrEmpty(identityModel.get("departmentNumber"))){
              locationID = identityModel.get("buildingId");  
        			depID = identityModel.get("departmentNumber");  
              String businessUnit = getBusinessCode(depID,locationID);
              if(Util.isNotNullOrEmpty(businessUnit)){
             		 identityModel.put("businessUnit",getBusinessCode(depID,locationID));
        			}
            }
        		if(Util.isNotNullOrEmpty(identityModel.get("businessUnit"))){
              businessID = identityModel.get("businessUnit");       
              identityModel.put("businessUnitDescription",getBusinessDesc(businessID));
            }
        	}
        }
        return name;
      ]]></Source>
    </Script>
    <Transition to="Build Provisioning Plan"/>
  </Step>
  <Step action="call:buildPlanFromIdentityModel" icon="plan" name="Build Provisioning Plan" posX="1218" posY="10" resultVariable="plan">
    <Arg name="identityModel" value="ref:identityModel"/>
    <Transition to="Call LCM Create"/>
  </Step>
  <Step icon="Default" name="Call LCM Create" posX="1508" posY="10">
    <Arg name="identityModel" value="ref:identityModel"/>
    <Arg name="approvalScheme" value="none"/>
    <Arg name="fallbackApprover"/>
    <Arg name="endOnManualWorkItems"/>
    <Arg name="userEmailTemplate" value="none"/>
    <Arg name="policiesToCheck"/>
    <Arg name="workItemPriority"/>
    <Arg name="project"/>
    <Arg name="source" value="LCM"/>
    <Arg name="identityDisplayName" value="ref:identityDisplayName"/>
    <Arg name="foregroundProvisioning" value="ref:foregroundProvisioning"/>
    <Arg name="approvalMode"/>
    <Arg name="batchRequestItemId"/>
    <Arg name="trace" value="ref:trace"/>
    <Arg name="doRefresh" value="true"/>
    <Arg name="endOnProvisioningForms"/>
    <Arg name="approverElectronicSignature"/>
    <Arg name="plan" value="ref:plan"/>
    <Arg name="flow" value="ref:flow"/>
    <Arg name="identityName" value="ref:identityName"/>
    <Arg name="notificationScheme" value="none"/>
    <Arg name="approvalSet"/>
    <Arg name="policyViolations"/>
    <Arg name="policyScheme" value="none"/>
    <Arg name="approvalForm"/>
    <Arg name="requesterEmailTemplate" value="none"/>
    <Arg name="approvalEmailTemplate" value="none"/>
    <Arg name="ticketManagementApplication"/>
    <Arg name="optimisticProvisioning"/>
    <Arg name="securityOfficerEmailTemplate"/>
    <Arg name="securityOfficerName"/>
    <Arg name="managerEmailTemplate" value="none"/>
    <Arg name="ticketId"/>
    <Description>Call the LCM Provisioning workflow with the plan that was created.  </Description>
    <Return name="identityRequestId" to="iiqIdentityRequestId"/>
    <Return name="identityID" to="identityID"/>
    <WorkflowRef>
      <Reference class="sailpoint.object.Workflow" name="Ascension-Workflow-LCM-CreateandUpdate"/>
    </WorkflowRef>
    <Transition to="Build Enable AD Plan">
      <Script>
        <Source><![CDATA[    
          import sailpoint.tools.Util;
          String enableAcc = wfcontext.getVariable("enableAccounts");

          if(Util.isNotNullOrEmpty(enableAcc) && Util.nullSafeCaseInsensitiveEq(enableAcc,"true")){
          return true;      
          }
          return false;

        ]]></Source>
      </Script>
    </Transition>
    <Transition to="Get Identity ID"/>
  </Step>
  <Step name="Get Identity ID" resultVariable="identityName">
    <Script>
      <Source><![CDATA[
       import sailpoint.object.Identity;
       if(Util.isNotNullOrEmpty(identityID)){
         Identity idObj = context.getObjectById(Identity.class,identityID);
         if(idObj != null){
       		identityName = idObj.getName();
          wfcontext.setVariable("identityName",identityName);
          //comment decache //context.decache(idObj);
         }
       }
       return identityName;
     ]]></Source>
    </Script>
    <Transition to="stop"/>
  </Step>
  <Step icon="plan" name="Build AD Plan" posX="1694" posY="10" resultVariable="planAD">
    <Arg name="identityDisplayName" value="ref:identityDisplayName"/>
    <Arg name="identityName" value="ref:identityName"/>
    <Arg name="planAD" value="ref:planAD"/>
    <Description>Process the user for AD account creation.</Description>
    <Script>
      <Source><![CDATA[
   			import sailpoint.api.SailPointContext;
        import sailpoint.object.Identity;
        import sailpoint.object.Form;
        import sailpoint.object.Application;
        import sailpoint.tools.Util;
        import sailpoint.object.ProvisioningPlan;
        import sailpoint.object.ProvisioningPlan.AccountRequest;
        import sailpoint.object.ProvisioningPlan.AttributeRequest;
        import sailpoint.object.Custom; 
        import sailpoint.object.Bundle;

        ProvisioningPlan plan = new ProvisioningPlan();
        if(null != planAD){
          plan = planAD;
        }
        
        Identity identityObject = context.getObjectByName(Identity.class, identityName);
        Custom custRole = context.getObjectByName(Custom.class,"Ascension-Custom-AD-DomainMapping");
        String domainAD = null;
 				String ministryAD = null;
        List roleNames = new ArrayList();
        
        if( null != identityObject){
        	domainAD = identityObject.getAttribute("domain");
        	ministryAD = identityObject.getAttribute("ministry");       	
        }
		if(Util.isNotNullOrEmpty(domainAD)){     
        	domainAD = domainConversion(domainAD);
   		}
       
         if (custRole != null && null != custRole.get("DomainOUMapping")) {
          domainMap = custRole.get("DomainOUMapping");
          if(null != domainMap && !domainMap.isEmpty() && null != domainMap.get(domainAD)){ 
          	roleNames = domainMap.get(domainAD).get("RoleName");
          }
          //comment decache //context.decache(custRole);
        } 
        
				if(null != roleNames && !roleNames.isEmpty()){
          ProvisioningPlan.AccountRequest acctRoleReq = new ProvisioningPlan.AccountRequest();
          acctRoleReq.setApplication("IIQ");
          acctRoleReq.setNativeIdentity(identityName);
          acctRoleReq.setOperation(ProvisioningPlan.AccountRequest.Operation.Modify);    
          for (String roleName: roleNames) {
            AttributeRequest attReq = new AttributeRequest(ProvisioningPlan.ATT_IIQ_ASSIGNED_ROLES , ProvisioningPlan.Operation.Add, roleName);
          
            acctRoleReq.add(attReq);                
          }

          plan.add(acctRoleReq);          

          if(null != identityObject){
        		plan.setIdentity(identityObject);
          	//comment decache //context.decache(identityObject);
          }
        }
        return plan;
      ]]></Source>
    </Script>
    <Transition to="RequestInitialize" when="script:(null != planAD &amp;&amp; !planAD.isEmpty())"/>
    <Transition to="stop"/>
  </Step>
  <Step name="Clean IdentityModel and Set IdentityName" posX="1150" posY="242" resultVariable="identityName">
    <Arg name="identityModel" value="ref:identityModel"/>
    <Description>
      Set the identityName workflow variable based on the reenable form input and clean identitymodel
    </Description>
    <Script>
      <Source><![CDATA[
        import sailpoint.object.Custom;

        
        String identityName = null;
        
        String locationID = "";
        String depID = "";
        String businessID ="";
        String locationName = "";
        String depName = "";
        
        
         if (identityModel != null && identityModel.get("partialFormUser") != null) {
        	String[] name = identityModel.get("partialFormUser").split(",");      
        identityName = name[0];
        	identityModel.put("name",identityName);
        	wfcontext.setVariable("flow","Bulk Update Contractor Identity");
          identityModel.remove("partialFormUser");
          if (identityModel.get("creationCheckbox") != null) {
            identityModel.remove("creationCheckbox");
          }
        	identityModel.put("manualTerm","No");
        } 
        
        if(identityModel != null && Util.nullSafeCaseInsensitiveEq(identityModel.get("domain"),"amita")){
         if(Util.isNotNullOrEmpty(identityModel.get("buildingId"))){
              locationName = identityModel.get("buildingId");       
              identityModel.put("location",getLocationName(locationName));
              identityModel.put("locationDescription",getLocationName(locationName));
            }
            if(Util.isNotNullOrEmpty(identityModel.get("departmentNumber"))){
              depNum = identityModel.get("departmentNumber");       
              identityModel.put("department",getDepartmentName(depNum));
            }
        		if(Util.isNotNullOrEmpty(identityModel.get("buildingId")) && Util.isNotNullOrEmpty(identityModel.get("departmentNumber"))){
              locationID = identityModel.get("buildingId");  
        			depID = identityModel.get("departmentNumber"); 
              String businessUnit = getBusinessCode(depID,locationID);
              if(Util.isNotNullOrEmpty(businessUnit)){
             		 identityModel.put("businessUnit",getBusinessCode(depID,locationID));
        			}
            }
        		if(Util.isNotNullOrEmpty(identityModel.get("businessUnit"))){
              businessID = identityModel.get("businessUnit");       
              identityModel.put("businessUnitDescription",getBusinessDesc(businessID));
            }
        	}
        
        Custom contractorCustom = context.getObjectByName(Custom.class, "Ascension-Custom-ContractorConfiguration");
        if (contractorCustom != null) {
        	List metadataAttributes = contractorCustom.get("identityModelMetadata");
        	if (metadataAttributes != null && !metadataAttributes.isEmpty()) {
            for(String attr : metadataAttributes) {
              identityModel.remove(attr);
            }
          }
        	//comment decache //context.decache(contractorCustom);
        }
        
        return identityName;
      ]]></Source>
    </Script>
    <Transition to="Build Enable Plan"/>
  </Step>
  <Step icon="plan" name="Build Enable Plan" posX="1500" posY="242" resultVariable="plan">
    <Arg name="identityName" value="ref:identityName"/>
    <Arg name="identityModel" value="ref:identityModel"/>
    <Description>Process the user to enable Account.</Description>
    <Script>
      <Source><![CDATA[
        import sailpoint.api.SailPointContext;
        import sailpoint.object.Identity;
        import sailpoint.tools.Util;
        import sailpoint.object.ProvisioningPlan;
        import sailpoint.object.ProvisioningPlan.AccountRequest;
        import sailpoint.object.ProvisioningPlan.AttributeRequest;
        import sailpoint.object.ProvisioningPlan.Operation;
        
        ProvisioningPlan plan = new ProvisioningPlan();
        Identity identityObject = null; 
        String identityAttribute = null;
      	String formAttribute = null;
              
          
        if(null !=identityName){ 
        	identityObject = context.getObjectByName(Identity.class, identityName);
        
        	if(null != identityObject){ 
        		List attributeList = new ArrayList(identityModel.keySet());        		
        		AccountRequest iiqAcctReq = new AccountRequest();
            iiqAcctReq.setApplication("IIQ");
            iiqAcctReq.setNativeIdentity(identityName);
            iiqAcctReq.setOperation(AccountRequest.Operation.Modify);
						if(null != attributeList && !attributeList.isEmpty()){
              for(String eachAttribute : attributeList) { 
                if(eachAttribute != null && (eachAttribute.equals("ssn") || eachAttribute.equals("dob"))) {
                //handling encrypted attributes separately 

                if (identityObject.getAttribute(eachAttribute) != null  && decryptAES(identityObject.getAttribute(eachAttribute)) != null) {
                  identityAttribute = decryptAES(identityObject.getAttribute(eachAttribute));
                }
                else{
                	identityAttribute = identityObject.getAttribute(eachAttribute);
                }
        
                if (identityModel != null && identityModel.get(eachAttribute) != null && decryptAES(identityModel.get("eachAttribute")) != null) {
                  formAttribute = decryptAES(identityModel.get(eachAttribute));
                }
        		else{
        		  formAttribute = identityModel.get(eachAttribute);
				}
                if (!Util.nullSafeEq(identityAttribute, formAttribute, true)) {
                  iiqAcctReq.add(new AttributeRequest(eachAttribute, ProvisioningPlan.Operation.Set, identityModel.get(eachAttribute)));                
                }
              }
              else 	if ( !Util.nullSafeEq(identityObject.getAttribute(eachAttribute), identityModel.get(eachAttribute), true) ) {                 
                   iiqAcctReq.add(new AttributeRequest(eachAttribute, ProvisioningPlan.Operation.Set, identityModel.get(eachAttribute)));                
                }        
              }	
        		}        	
        
        	if(identityObject.isInactive()){	
       			iiqAcctReq.add(new AttributeRequest("inactive", ProvisioningPlan.Operation.Set, false)); 
        		wfcontext.setVariable("enableAccounts","true");
       		}
            plan.add(iiqAcctReq);
            plan.setIdentity(identityObject);
            //comment decache //context.decache(identityObject);      
        	}
        } 
        return plan;
      ]]></Source>
    </Script>
    <Transition to="Call LCM Create" when="script:(null != plan &amp;&amp; !plan.isEmpty())"/>
    <Transition to="Stop"/>
  </Step>
  <Step icon="plan" name="Build Enable AD Plan" posX="1666" posY="126" resultVariable="planAD">
    <Arg name="identityName" value="ref:identityName"/>
    <Arg name="identityModel" value="ref:identityModel"/>
    <Description>Process the user to enable AD Account.</Description>
    <Script>
      <Source><![CDATA[
       import sailpoint.api.SailPointContext;
        import sailpoint.object.Identity;
        import sailpoint.tools.Util;
        import sailpoint.object.Application;
        import sailpoint.object.ProvisioningPlan;
        import sailpoint.object.ProvisioningPlan.AccountRequest;
        import sailpoint.object.ProvisioningPlan.AttributeRequest;
        import sailpoint.object.Custom;  
        import java.util.Iterator;
        import sailpoint.object.Link;
        import sailpoint.object.ProvisioningPlan.Operation;
        import sailpoint.api.PasswordGenerator;
        import sailpoint.object.PasswordPolicy;
        import java.text.Format;
        import java.text.SimpleDateFormat;

        ProvisioningPlan plan = new ProvisioningPlan();
        
                

        Identity identityObject = null;
        String appName = null;
        String accountName = null;
        String appType = null;
        String adExpDate = null;
        String valueCN = null ;
        String activeOU = null;
        String domainAD = null;
 				String ministryAD = null;
        String locationID= null;
        Map domainMap = new HashMap();
        HashMap activeOUMap = new HashMap();
        List listOfAccounts=new ArrayList();
        
        Custom custom = context.getObjectByName(Custom.class,"Ascension-Custom-AD-DomainMapping");
        Custom customApp = context.getObjectByName(Custom.class, "Ascension-Custom-ContractorConfiguration");
        
        if(null != identityModel && Util.isNotNullOrEmpty(identityModel.get("ctrexpDt"))){
          adExpDate = getADFormatedDateString(identityModel.get("ctrexpDt"));       	
        }                  
          
        if(null !=identityName){   
        
        	identityObject = context.getObjectByName(Identity.class, identityName);
        
          if(null != identityObject){ 
            domainAD = identityObject.getAttribute("domain");
            ministryAD = identityObject.getAttribute("ministry");  
        		locationID = identityObject.getAttribute("buildingId");
          
        	if(Util.isNotNullOrEmpty(domainAD)){     
        	domainAD = domainConversion(domainAD);
   		}
            if(custom != null && null != custom.get("DomainOUMapping")){
              domainMap = custom.get("DomainOUMapping");              
              //comment decache //context.decache(custom);
            }
        
        if(null != customApp && null != customApp.get("IncludeReenableApplications")){
        listOfAccounts=customApp.get("IncludeReenableApplications");
        }
        	       
          List linksAccount= (List) identityObject.getLinks();        
        	if( null != linksAccount){
          Iterator itrlinksAccount = linksAccount.iterator();
            while (itrlinksAccount.hasNext()){
              Link account = (Link) itrlinksAccount.next();
              ProvisioningPlan.AccountRequest acctReq = new ProvisioningPlan.AccountRequest();
        			ProvisioningPlan.AccountRequest acctReqModify = new ProvisioningPlan.AccountRequest();
        			
              if(null != account  && null != account.getApplication()){
                appName=account.getApplicationName();
                accountName =account.getNativeIdentity();
        				appType = account.getApplication().getType();
        
                  if(Util.isNotNullOrEmpty(appName) && Util.isNotNullOrEmpty(accountName) && Util.isNotNullOrEmpty(appType) && appType.equalsIgnoreCase("Active Directory - Direct") && listOfAccounts.contains(appName)){
        
										
        						String principalName = account.getAttribute("msDS-PrincipalName");
                    String domainofAcc = "";
        
                    if(Util.isNotNullOrEmpty(principalName)){
                    	domainofAcc = getDomain(principalName);
        						}
                                                               

                    if(Util.nullSafeCaseInsensitiveEq(domainofAcc,domainAD)){
        
        						acctReq.setApplication(appName);
                    acctReq.setNativeIdentity(accountName);
                    acctReq.setOperation(ProvisioningPlan.AccountRequest.Operation.Enable);
                    plan.add(acctReq);
        
         
                    if(null != domainMap && !domainMap.isEmpty() && null != domainMap.get(domainAD)){  
                    activeOUMap = domainMap.get(domainAD).get("activeOU");
                    if(null != activeOUMap && !activeOUMap.isEmpty()){
        						if(Util.isNotNullOrEmpty(locationID) && Util.isNotNullOrEmpty(activeOUMap.get(locationID))){
                    activeOU = activeOUMap.get(locationID);
                    }
                    else{
                    activeOU = activeOUMap.get("DEFAULT");
                    }
                    }	
       							}								

                    String password = null;

                    PasswordPolicy policy = context.getObjectByName(PasswordPolicy.class, "AD Default Password Policy"); 

                   
					if(policy!=null)
                    {       
                    password = new PasswordGenerator(context).generatePassword(policy);
                    }        
        							        
        						acctReqModify.setApplication(appName);
                    acctReqModify.setNativeIdentity(accountName);
                    acctReqModify.setOperation(ProvisioningPlan.AccountRequest.Operation.Modify);
        
                    List attreqs = new ArrayList();
                    if (!Util.nullSafeCaseInsensitiveEq(identityObject.getStringAttribute("domain"),"AMITA")){
        							if (Util.isNotNullOrEmpty(adExpDate)){
        								attreqs.add(new AttributeRequest("accountExpires", ProvisioningPlan.Operation.Set, adExpDate));
        								description = "";
        							}                      
        						}
        						else if(Util.isNotNullOrEmpty(identityObject.getAttribute("title")) && Util.isNotNullOrEmpty(identityObject.getAttribute("department"))){
           						description = identityObject.getAttribute("title")+" - "+identityObject.getAttribute("department");          
          					}
        
        						attreqs.add(new AttributeRequest("description", ProvisioningPlan.Operation.Set, description));
        
       							 if (Util.isNotNullOrEmpty(password)){
                      attreqs.add(new AttributeRequest("password", ProvisioningPlan.Operation.Set, password));
                     }

                     if (Util.isNotNullOrEmpty(accountName)) 
                     {
                      valueCN= accountName.substring(0, accountName.indexOf("OU=")-1);
										 }

                    if(Util.isNotNullOrEmpty(activeOU)){
                      attreqs.add(new AttributeRequest("AC_NewParent", ProvisioningPlan.Operation.Set, activeOU));
                    }
        
                    if(Util.isNotNullOrEmpty(valueCN)){
                      attreqs.add(new AttributeRequest("AC_NewName", ProvisioningPlan.Operation.Set, valueCN));
                    }
                    acctReqModify.setAttributeRequests(attreqs);
        						plan.add(acctReqModify);
        						}
        						}
                   else if (Util.isNotNullOrEmpty(appName) && Util.isNotNullOrEmpty(accountName)){
                    if(listOfAccounts.contains(appName)){
                      acctReq.setApplication(appName);
                      acctReq.setNativeIdentity(accountName);
                      acctReq.setOperation(ProvisioningPlan.AccountRequest.Operation.Enable);
                      plan.add(acctReq);                    
                    }  
                    }
                  }
                } 
       				 	if(null != itrlinksAccount){
                	Util.flushIterator(itrlinksAccount);
              	} 
        			}                   
            }        		
            plan.setIdentity(identityObject);
            //comment decache //context.decache(identityObject);
        	}
        return plan;
      ]]></Source>
    </Script>
    <Transition to="Build AD Plan"/>
  </Step>
  <Step icon="Task" name="RequestInitialize" posX="1856" posY="10">
    <Arg name="formTemplate" value="Identity Update"/>
    <Arg name="identityName" value="ref:identityName"/>
    <Arg name="enableRetryRequest"/>
    <Arg name="allowRequestsWithViolations"/>
    <Arg name="endOnManualWorkItems"/>
    <Arg name="policiesToCheck"/>
    <Arg name="workItemPriority" value="ref:workItemPriority"/>
    <Arg name="workItemComments"/>
    <Arg name="source" value="ref:source"/>
    <Arg name="violationReviewDecision"/>
    <Arg name="policyScheme" value="none"/>
    <Arg name="identityDisplayName" value="ref:identityDisplayName"/>
    <Arg name="requireViolationReviewComments"/>
    <Arg name="identityRequest"/>
    <Arg name="trace" value="ref:trace"/>
    <Arg name="enableApprovalRecommendations"/>
    <Arg name="asyncCacheRefresh"/>
    <Arg name="endOnProvisioningForms"/>
    <Arg name="optimisticProvisioning" value="ref:optimisticProvisioning"/>
    <Arg name="plan" value="ref:planAD"/>
    <Arg name="flow" value="Bulk Reenable Contractor"/>
    <Arg name="launcher" value="ref:launcher"/>
    <Description>
      Call the standard subprocess to initialize the request, this includes
      auditing, building the approvalset, compiling the plan into 
      project and checking policy violations.
    </Description>
    <Return name="project" to="project"/>
    <Return name="approvalSet" to="cart"/>
    <Return name="identityRequestId" to="identityRequestId"/>
    <Return name="policyViolations" to="policyViolations"/>
    <WorkflowRef>
      <Reference class="sailpoint.object.Workflow" name="Identity Request Initialize"/>
    </WorkflowRef>
    <Transition to="Provision"/>
  </Step>
  <Step condition="script:!((size(policyViolations) &gt; 0 ) &amp;&amp; (policyScheme.equals(&quot;fail&quot;)))" icon="Task" name="Provision" posX="2022" posY="10">
    <Arg name="formTemplate" value="Identity Update"/>
    <Arg name="approvalScheme" value="none"/>
    <Arg name="identityName" value="ref:identityName"/>
    <Arg name="fallbackApprover" value="ref:fallbackApprover"/>
    <Arg name="approvalSet"/>
    <Arg name="manualActionsEmailTemplate" value="Pending Manual Changes"/>
    <Arg name="workItemComments"/>
    <Arg name="workItemPriority" value="ref:workItemPriority"/>
    <Arg name="project" value="ref:project"/>
    <Arg name="identityRequestId" value="ref:identityRequestId"/>
    <Arg name="policyScheme" value="none"/>
    <Arg name="splitProvisioning"/>
    <Arg name="saveUnmanagedPlan"/>
    <Arg name="foregroundProvisioning" value="ref:foregroundProvisioning"/>
    <Arg name="noTriggers" value="true"/>
    <Arg name="identityDisplayName" value="ref:identityDisplayName"/>
    <Arg name="trace" value="ref:trace"/>
    <Arg name="saveUnmanagedPlan_WithProjectArgument"/>
    <Arg name="recompile"/>
    <Arg name="optimisticProvisioning" value="ref:optimisticProvisioning"/>
    <Arg name="plan"/>
    <Arg name="launcher" value="ref:launcher"/>
    <Description>
      Call the standard subprocess that will process the 
      approval decisions and do provisioning.  This
      includes calling any configured provisioning 
      connectors and building manual actions.
    </Description>
    <Return name="project" to="project"/>
    <WorkflowRef>
      <Reference class="sailpoint.object.Workflow" name="Identity Request Provision"/>
    </WorkflowRef>
    <Transition to="Finalize"/>
  </Step>
  <Step catches="complete" condition="script:!((size(policyViolations) &gt; 0 ) &amp;&amp; (policyScheme.equals(&quot;fail&quot;)))" icon="Task" name="Finalize" posX="2124" posY="10">
    <Arg name="trace" value="ref:trace"/>
    <Arg name="identityName" value="ref:identityName"/>
    <Arg name="autoVerifyIdentityRequest"/>
    <Arg name="approvalSet" value="ref:cart"/>
    <Arg name="ticketManagementApplication"/>
    <Arg name="project" value="ref:project"/>
    <Arg name="workItemPriority" value="ref:workItemPriority"/>
    <Arg name="identityRequestId" value="ref:identityRequestId"/>
    <Arg name="ticketDataGenerationRule"/>
    <Description>
      Call the standard subprocess that can audit/finalize the request.
    </Description>
    <WorkflowRef>
      <Reference class="sailpoint.object.Workflow" name="Identity Request Finalize"/>
    </WorkflowRef>
    <Transition to="Refresh Identity"/>
  </Step>
  <Step action="call:refreshIdentity" condition="ref:doRefresh" icon="Task" name="Refresh Identity" posX="2218" posY="10">
    <Arg name="identityName">
      <Script>
        <Source><![CDATA[
       import sailpoint.object.Identity;
       
       if(Util.isNotNullOrEmpty(identityID)){
         Identity idObj = context.getObjectById(Identity.class,identityID);
         if(idObj != null){
       		identityName = idObj.getName();
          wfcontext.setVariable("identityName",identityName);
          //comment decache //context.decache(idObj);
         }
       }
       return identityName;
     ]]></Source>
      </Script>
    </Arg>
    <Arg name="provision" value="true"/>
    <Arg name="correlateEntitlements" value="true"/>
    <Arg name="synchronizeAttributes" value="false"/>
    <Arg name="promoteAttributes" value="false"/>
    <Arg name="processTriggers" value="true"/>
    <Arg name="doManualActions" value="ref:doManualActions"/>
    <Transition to="stop"/>
  </Step>
  <Step icon="task" name="Set ExternalTicketId In identityRequest" posX="351" posY="10">
    <Description>Set ExternalTicketId In identityRequest</Description>
    <Script>
      <Source><![CDATA[
      import sailpoint.object.IdentityRequest;
      import sailpoint.api.ObjectUtil;
        
      IdentityRequest iRequest = ObjectUtil.transactionLock(context, IdentityRequest.class, identityRequestId);
			if(iRequest!=null){
          iRequest.setExternalTicketId(iiqIdentityRequestId);
          context.saveObject(iRequest);
          context.commitTransaction();
          //comment decache //context.decache(iRequest);
       }
        ]]></Source>
    </Script>
    <Transition to="stop"/>
  </Step>
  <Step icon="Stop" name="stop" posX="2376" posY="10"/>
</Workflow>