<?xml version='1.0' encoding='UTF-8'?>
<!DOCTYPE Application PUBLIC "sailpoint.dtd" "sailpoint.dtd">
<Application connector="sailpoint.connector.DelimitedFileConnector" featuresString="DIRECT_PERMISSIONS, NO_RANDOM_ACCESS, DISCOVER_SCHEMA" icon="enterpriseIcon" name="Access Badge - Photo ID Request - ININD - Cancer Center" profileClass="" type="DelimitedFile">
  <AccountCorrelationConfig>
    <Reference class="sailpoint.object.CorrelationConfig" name="Ascension-DisconnectedApps-Correlation Config"/>
  </AccountCorrelationConfig>
  <Attributes>
    <Map>
      <entry key="PassphraseForPrivateKey"/>
      <entry key="PrivateKeyFilePath"/>
      <entry key="acceleratorPackEnabled"/>
      <entry key="accountCorrelationAttrExpression"/>
      <entry key="accountCreateConditionalRule"/>
      <entry key="accountCreateEntitlements"/>
      <entry key="accountDisableAttrExpression"/>
      <entry key="accountLockAttrExpression"/>
      <entry key="acctAggregationEnd">
        <value>
          <Date>1694192234719</Date>
        </value>
      </entry>
      <entry key="acctAggregationStart">
        <value>
          <Date>1694192223200</Date>
        </value>
      </entry>
      <entry key="additionalAppBusApprovalRule"/>
      <entry key="additionalAppBusApprovers"/>
      <entry key="afterProvisioningRule"/>
      <entry key="apAdditionalApplicationAfterProvisioningRule"/>
      <entry key="apAdditionalApplicationCorrelationRule"/>
      <entry key="apAdditionalApplicationCreationRule"/>
      <entry key="apAdditionalApplicationCustomizationRule"/>
      <entry key="apAdditionalApplicationMCustomizationRule"/>
      <entry key="apAdditionalApplicationMGroupRefreshRule"/>
      <entry key="apAdditionalApplicationPreIterateRule"/>
      <entry key="apAfterMoverJoiner">
        <value>
          <Boolean/>
        </value>
      </entry>
      <entry key="apAfterRehireAttrSync">
        <value>
          <Boolean/>
        </value>
      </entry>
      <entry key="apAttributeSyncEligibleRule"/>
      <entry key="apBeforeMoverAttrSync">
        <value>
          <Boolean/>
        </value>
      </entry>
      <entry key="apPopulationReverseLeaverOptions"/>
      <entry key="appBusApprovalRule"/>
      <entry key="appBusApprovers"/>
      <entry key="ascBusinessApplication" value="Access Badge - Photo ID Request - ININD - Cancer Center"/>
      <entry key="authoritativeEmployee"/>
      <entry key="authoritativeNonEmployee"/>
      <entry key="beforeProvisioningRule"/>
      <entry key="beforemoverPrimaryaccount">
        <value>
          <Boolean/>
        </value>
      </entry>
      <entry key="birthrightEntAttrExpression"/>
      <entry key="busApp">
        <value>
          <Boolean/>
        </value>
      </entry>
      <entry key="commentsAttr"/>
      <entry key="commentsValue"/>
      <entry key="compositeDefinition"/>
      <entry key="delimiter" value=","/>
      <entry key="displayFormRule"/>
      <entry key="evaluateCreateprovpolicy"/>
      <entry key="file" value="\\andc1wapp0147.ds.sjhs.com\AppAggregation\Access Badge - Photo ID Request - ININD - Cancer Center.csv"/>
      <entry key="filetransport" value="local"/>
      <entry key="filterEmptyRecords">
        <value>
          <Boolean>true</Boolean>
        </value>
      </entry>
      <entry key="ftpsAuthMethod" value="password"/>
      <entry key="ftpsClientCertificateFilePath"/>
      <entry key="ftpsClientCertificatePassphrase"/>
      <entry key="group.filetransport" value="local"/>
      <entry key="group.filterEmptyRecords">
        <value>
          <Boolean>true</Boolean>
        </value>
      </entry>
      <entry key="group.partitionMode" value="auto"/>
      <entry key="hardPolicyviolations"/>
      <entry key="hasHeader">
        <value>
          <Boolean>true</Boolean>
        </value>
      </entry>
      <entry key="indexColumn" value="Username"/>
      <entry key="isCaseInsensitiveMerge">
        <value>
          <Boolean/>
        </value>
      </entry>
      <entry key="isSortedByIndexColumn">
        <value>
          <Boolean/>
        </value>
      </entry>
      <entry key="joinerEnabled"/>
      <entry key="joinerPopulationRegex"/>
      <entry key="joinerRoles"/>
      <entry key="mergeColumns">
        <value>
          <List>
            <String>Role</String>
          </List>
        </value>
      </entry>
      <entry key="mergeRows">
        <value>
          <Boolean>true</Boolean>
        </value>
      </entry>
      <entry key="moveAccountContainer"/>
      <entry key="moverExtendedRule"/>
      <entry key="moverProcess" value="Do Nothing"/>
      <entry key="moverRevocation" value="Do Nothing"/>
      <entry key="nativeChangeDetectionAttributeScope" value="entitlements"/>
      <entry key="nativeChangeDetectionAttributes"/>
      <entry key="nativeChangeDetectionEnabled">
        <value>
          <Boolean/>
        </value>
      </entry>
      <entry key="nativeChangeDetectionOperations"/>
      <entry key="parseType" value="delimited"/>
      <entry key="partitionMode" value="auto"/>
      <entry key="port"/>
      <entry key="primarySyncaccounts">
        <value>
          <Boolean/>
        </value>
      </entry>
      <entry key="primarypasswordSyncaccounts">
        <value>
          <Boolean/>
        </value>
      </entry>
      <entry key="privilegedAccountAttrExpression"/>
      <entry key="privilegedEntAttrExpression"/>
      <entry key="rehireExtendedRule"/>
      <entry key="rehirePrimaryaccount">
        <value>
          <Boolean/>
        </value>
      </entry>
      <entry key="rehireProcess" value="Do Nothing"/>
      <entry key="removeEntitlementLeaverExceptionExpression"/>
      <entry key="renameLDAPaccount">
        <value>
          <Boolean/>
        </value>
      </entry>
      <entry key="requestorFormRole"/>
      <entry key="reverseTerminationExtendedRule"/>
      <entry key="reverseleaverProcess" value="Do Nothing"/>
      <entry key="scramblePasswordAttr"/>
      <entry key="sftpAuthMethod" value="password"/>
      <entry key="skipSupervisorApproval"/>
      <entry key="snowAssignmentGroup" value="7cfc60e91b632054e7121025bd4bcb32"/>
      <entry key="snowAssignmentGroupName" value="ININD/APP/Access Badge Photo ID"/>
      <entry key="softPolicyviolations"/>
      <entry key="stopIfLineHasWrongColumnLength">
        <value>
          <Boolean/>
        </value>
      </entry>
      <entry key="sysDescriptions">
        <value>
          <Map>
            <entry key="en_US"/>
          </Map>
        </value>
      </entry>
      <entry key="templateApplication" value="DelimitedFile Template"/>
      <entry key="terminationExtendedRule"/>
      <entry key="terminationProcess" value="Do Nothing"/>
      <entry key="xDays"/>
      <entry key="xDeleteDays"/>
    </Map>
  </Attributes>
  <Owner>
    <Reference class="sailpoint.object.Identity" name="IDM Team"/>
  </Owner>
  <ProvisioningForms>
    <Form name="INEVA/ININD - Access Badge - Photo ID Request-CreatePolicy" objectType="account" type="Create">
      <Attributes>
        <Map>
          <entry key="pageTitle" value="INEVA/ININD - Access Badge - Photo ID Request-CreatePolicy"/>
        </Map>
      </Attributes>
      <Section name="Section 1">
        <Field displayName="EmployeeID" name="EmployeeID" required="true" reviewRequired="true" type="string">
          <Script>
            <Source><![CDATA[import sailpoint.tools.Util;
              if(Util.isNotNullOrEmpty(identity.getAttribute("employeeId"))){
              return identity.getAttribute("employeeId");
              }
              else{
              return null;
              }]]></Source>
          </Script>
        </Field>
        <Field displayName="Lastname" name="Lastname" type="string">
          <Attributes>
            <Map>
              <entry key="readOnly" value="true"/>
            </Map>
          </Attributes>
          <Script>
            <Source><![CDATA[import sailpoint.tools.Util;
              if(Util.isNotNullOrEmpty(identity.getAttribute("lastname"))){
              return identity.getAttribute("lastname");
              }
              else{
              return null;
              }]]></Source>
          </Script>
        </Field>
        <Field displayName="Firstname" name="Firstname" type="string">
          <Attributes>
            <Map>
              <entry key="readOnly" value="true"/>
            </Map>
          </Attributes>
          <Script>
            <Source><![CDATA[import sailpoint.tools.Util;
              if(Util.isNotNullOrEmpty(identity.getAttribute("firstname"))){
              return identity.getAttribute("firstname");
              }
              else{
              return null;
              }]]></Source>
          </Script>
        </Field>
        <Field displayName="Preferred Name" dynamic="true" name="Preferred Name" type="string"/>
        <Field displayName="Credential" name="Credential" required="true" type="string">
          <AllowedValuesDefinition>
            <Value>
              <List>
                <String>Physician</String>
                <String>PA</String>
                <String>RN</String>
                <String>NP</String>
                <String>No Credential</String>
                <String>MA</String>
                <String>LPN</String>
                <String>Clinical Tech</String>
                <String>Social Worker</String>
                <String>Pharmacist</String>
              </List>
            </Value>
          </AllowedValuesDefinition>
        </Field>
        <Field displayName="Role" dynamic="true" name="Role" type="string"/>
        <Field displayName="Department" name="Department" type="string">
          <Attributes>
            <Map>
              <entry key="readOnly" value="true"/>
            </Map>
          </Attributes>
          <Script>
            <Source><![CDATA[import sailpoint.tools.Util;
              if(Util.isNotNullOrEmpty(identity.getAttribute("department"))){
              return identity.getAttribute("department");
              }
              else{
              return null;
              }]]></Source>
          </Script>
        </Field>
        <Field displayName="Reason For Badge" name="Reason For Badge" required="true" type="string">
          <AllowedValuesDefinition>
            <Value>
              <List>
                <String>New Hire</String>
                <String>Access Change or Addition - specify</String>
                <String>Rehire</String>
                <String>Transfer</String>
                <String>Information Update - specifiy</String>
                <String>Lost</String>
                <String>Other-Specify</String>
              </List>
            </Value>
          </AllowedValuesDefinition>
        </Field>
        <Field displayName="Is This a Secondary Position?" name="Is This a Secondary Position?" required="true" type="string">
          <AllowedValuesDefinition>
            <Value>
              <List>
                <String>Yes</String>
                <String>No</String>
              </List>
            </Value>
          </AllowedValuesDefinition>
        </Field>
        <Field displayName="Is this a direct PMCH position?" name="Is this a direct PMCH position?" required="true" type="string">
          <AllowedValuesDefinition>
            <Value>
              <List>
                <String>Yes</String>
                <String>No</String>
              </List>
            </Value>
          </AllowedValuesDefinition>
        </Field>
        <Field displayName="Specific Door Access " name="Specific Door Access " required="true" type="string">
          <AllowedValuesDefinition>
            <Value>
              <List>
                <String>Standard Door Access to Above Location</String>
                <String>No Door Access</String>
                <String>Specific Door Access</String>
              </List>
            </Value>
          </AllowedValuesDefinition>
        </Field>
        <Field displayName="Notes Field" name="Notes Field" reviewRequired="true" type="string"/>
        <Field displayName="EmailAddress" name="EmailAddress" type="string">
          <Attributes>
            <Map>
              <entry key="readOnly" value="true"/>
            </Map>
          </Attributes>
          <Script>
            <Source><![CDATA[import sailpoint.tools.Util;
              if(Util.isNotNullOrEmpty(identity.getAttribute("email"))){
              return identity.getAttribute("email");
              }
              else{
              return null;
              }]]></Source>
          </Script>
        </Field>
        <Field displayName="Username" name="Username" type="string">
          <Attributes>
            <Map>
              <entry key="readOnly" value="true"/>
            </Map>
          </Attributes>
          <Script>
            <Source><![CDATA[return identity.getName();]]></Source>
          </Script>
        </Field>
        <Field displayName="Manager" name="Manager" type="string">
          <AllowedValuesDefinition>
            <Script>
              <Source><![CDATA[import sailpoint.tools.Util;
              if(Util.isNotNullOrEmpty(identity.getAttribute("manager"))){
              return identity.getAttribute("manager");
              }
              else{
              return null;
              }]]></Source>
            </Script>
          </AllowedValuesDefinition>
        </Field>
        <Field displayName="Facility" name="Facility" type="string">
          <AllowedValuesDefinition>
            <Script>
              <Source><![CDATA[import sailpoint.tools.Util;
              if(Util.isNotNullOrEmpty(identity.getAttribute("locationDescription"))){
              return identity.getAttribute("locationDescription");
              }
              else{
              return null;
              }]]></Source>
            </Script>
          </AllowedValuesDefinition>
        </Field>
        <Field displayName="Badge Number" name="Badge Number" required="true" type="string"/>
        <Field displayName="Type of badge" name="Type of badge" required="true" type="string">
          <AllowedValuesDefinition>
            <Value>
              <List>
                <String>Associate</String>
                <String>Contracted Physician</String>
                <String>CWR/Indpendent Contractor</String>
                <String>Employed Physician</String>
                <String>Independent Provider</String>
                <String>MWF associate</String>
                <String>PMCH Associate</String>
                <String>Student</String>
                <String>Volunteer</String>
              </List>
            </Value>
          </AllowedValuesDefinition>
        </Field>
        <Field displayName="Badge Admin Notes Field" name="Badge Admin Notes Field" reviewRequired="true" type="string"/>
        <Field displayName="Transfer" name="Transfer" reviewRequired="true" type="string">
          <AllowedValuesDefinition>
            <Value>
              <List>
                <String>Associate to CWR/MWF associate</String>
                <String>CWR/MWF associate to Associate</String>
                <String>Facility and/or Department to new Facility/Dept</String>
              </List>
            </Value>
          </AllowedValuesDefinition>
        </Field>
      </Section>
    </Form>
  </ProvisioningForms>
  <Schemas>
    <Schema displayAttribute="Username" identityAttribute="Username" instanceAttribute="" nativeObjectType="account" objectType="account" permissionsRemediationModificationType="None">
      <AttributeDefinition name="Username" type="string">
        <Description/>
      </AttributeDefinition>
      <AttributeDefinition name="Firstname" type="string">
        <Description/>
      </AttributeDefinition>
      <AttributeDefinition name="Lastname" type="string">
        <Description/>
      </AttributeDefinition>
      <AttributeDefinition name="EmployeeNumber" type="string">
        <Description/>
      </AttributeDefinition>
      <AttributeDefinition name="EmailAddress" type="string">
        <Description/>
      </AttributeDefinition>
      <AttributeDefinition name="Department" type="string">
        <Description/>
      </AttributeDefinition>
      <AttributeDefinition entitlement="true" managed="true" multi="true" name="Role" type="string">
        <Description/>
      </AttributeDefinition>
    </Schema>
  </Schemas>
  <ApplicationScorecard/>
</Application>