<?xml version='1.0' encoding='UTF-8'?>
<!DOCTYPE EmailTemplate PUBLIC "sailpoint.dtd" "sailpoint.dtd">
<EmailTemplate name="Ascension-EmailTemplate-ManagerNotification-NewUserIntialLogin">
  <Body>
    #set($ctx = $spTools.class.forName("sailpoint.api.SailPointFactory").getMethod("getFactory", null).invoke(null,null).getCurrentContext())
    #set($ruleObj = $ctx.getObjectByName($spTools.class.forName("sailpoint.object.Rule"), "Rule-Framework-Header-Footer-StyleSheet")) 
    #set($ruleArgs = { 
    "keyEmailTemplate"  : "styleSheet"
    }) 
    #set($styleSheet = $ctx.runRule($ruleObj, $ruleArgs))
    #if( $ruleObj )
    $ctx.decache($ruleObj)
    #end
    #set($ruleObj = $ctx.getObjectByName($spTools.class.forName("sailpoint.object.Rule"), "Rule-Framework-Header-Footer-StyleSheet")) 
    #set($ruleArgs = { 
    "keyEmailTemplate"  : "headerTemplate"
    }) 
    #set($headerTemplate = $ctx.runRule($ruleObj, $ruleArgs))
    #if( $ruleObj )
    $ctx.decache($ruleObj)
    #end
    #set($ruleObj = $ctx.getObjectByName($spTools.class.forName("sailpoint.object.Rule"), "Rule-Framework-Header-Footer-StyleSheet")) 
    #set($ruleArgs = { 
    "keyEmailTemplate"  : "footerTemplate"
    }) 
    #set($footerTemplate = $ctx.runRule($ruleObj, $ruleArgs))
    #if( $ruleObj )
    $ctx.decache($ruleObj)
    #end
    #set($ruleObj = $ctx.getObjectByName($spTools.class.forName("sailpoint.object.Rule"), "Rule-Server-Root-Path")) 
    #set($ruleArgs = {})
    #set($rootPath = $ctx.runRule($ruleObj, $ruleArgs))
    &lt;html>
    &lt;head>
    &lt;meta charset="UTF-8">	    
    #if($styleSheet)
    $styleSheet
    #end
    &lt;/head>
    &lt;body>
    #if( $headerTemplate )
    $headerTemplate
    #end
    &lt;br/>

      &lt;p>Hello,&lt;/p>

    &lt;p>The initial network password for $Map.get("Name") is #if($Map.get("Password"))$Map.get("Password")#end&lt;/p>
    &lt;p>Your password needs to be reset on the initial login.&lt;/p>
    
    &lt;p>For all associates follow step 1 below, additionally If you are located at a legacy Presence Health sites that use Meditech or Epic, AMG sites affiliated with Meditech/Epic hospitals 
    and/or are a remote associate who has an Ascension-issued device on the Presence Health Domain you must follow step 2 as well.&lt;/p>

    &lt;p>&amp;nbsp;&amp;nbsp;1) To reset your AMITA password go to the AHPM site :  https://ahpm.ascension.org For first time logon you will enter your username, temporary password provided above, and select “AMITA” from the drop down
			&lt;/p>
    &lt;p>&amp;nbsp;&amp;nbsp;2)If you are located at a legacy Presence Health sites, go to one of the two URLs below go to: https://remote.presencehealth.org/&lt;/p>

   
    &lt;p>For shared workstations at a legacy Presence Health location:&lt;/p>
		&lt;p>Go to:  https://appstore.presencehealth.net.&lt;/p>
    
    &lt;p>&amp;nbsp;&amp;nbsp;o Once logged in, find the gear icon in the upper right corner of the page and click “Account Settings.”&lt;/p>
    &lt;p>&amp;nbsp;&amp;nbsp;o Click “Change Password.”&lt;/p>
    &lt;p>&amp;nbsp;&amp;nbsp;o Fill in your old password, new password and confirm, then click “OK.”&lt;/p>



    &lt;p>NOTE: The password must meet the requirements:&lt;/p>
    &lt;p>&amp;nbsp;&amp;nbsp;o At least 12 characters long&lt;/p>
    &lt;p>&amp;nbsp;&amp;nbsp;o Contain three of the following: uppercase letters, lowercase letters, numbers or symbols&lt;/p>
    &lt;p>&amp;nbsp;&amp;nbsp;o Passwords cannot contain your personal information such as first or last name.&lt;/p>
    &lt;p>&amp;nbsp;&amp;nbsp;o The first 12 characters of the new password cannot match the first 12 characters of any previously used passwords.&lt;/p>
 

    &lt;p>Thank you,&lt;br/>
    The IAM Operations Team&lt;/p>
    #if( $footerTemplate )
    $footerTemplate
    #end
    &lt;/body>
    &lt;/html>
  </Body>
  <Description>
    Email Template for notifying managers when an employee's account(s) are modified.
    Note that in addition to the declared arguments, all workflow variables,
    Step arguments, and Approval arguments defined in the Workflow are
    also available.
  </Description>
  <Signature>
    <Inputs>
      <Argument name="Map" type="LinkedHashMap">
        <Description>The Workflow object being executed.</Description>
      </Argument>
      <Argument name="identityDisplayName" type="string">
        <Description>The display name of the Identity that is being changed.</Description>
      </Argument>
      <Argument name="operation" type="string">
        <Description>The display name of the Identity that is being changed.</Description>
      </Argument>
    </Inputs>
  </Signature>
  <Subject>Initial Login Instructions for New User</Subject>
</EmailTemplate>
