<?xml version='1.0' encoding='UTF-8'?>
<!DOCTYPE EmailTemplate PUBLIC "sailpoint.dtd" "sailpoint.dtd">
<EmailTemplate name="Ascension-EmailTemplate-Voalte-ManagerNotification">
  <Body>
    #set($ctx = $spTools.class.forName("sailpoint.api.SailPointFactory").getMethod("getFactory", null).invoke(null,null).getCurrentContext())
    #set($ruleObj = $ctx.getObjectByName($spTools.class.forName("sailpoint.object.Rule"), "Rule-Framework-Header-Footer-StyleSheet")) 
    #set($ruleArgs = { 
    "keyEmailTemplate"  : "styleSheet"
    }) 
    #set($styleSheet = $ctx.runRule($ruleObj, $ruleArgs))
    #if( $ruleObj )
    $ctx.decache($ruleObj)
    #end
    #set($ruleObj = $ctx.getObjectByName($spTools.class.forName("sailpoint.object.Rule"), "Rule-Framework-Header-Footer-StyleSheet")) 
    #set($ruleArgs = { 
    "keyEmailTemplate"  : "headerTemplate"
    }) 
    #set($headerTemplate = $ctx.runRule($ruleObj, $ruleArgs))
    #if( $ruleObj )
    $ctx.decache($ruleObj)
    #end
    #set($ruleObj = $ctx.getObjectByName($spTools.class.forName("sailpoint.object.Rule"), "Rule-Framework-Header-Footer-StyleSheet")) 
    #set($ruleArgs = { 
    "keyEmailTemplate"  : "footerTemplate"
    }) 
    #set($footerTemplate = $ctx.runRule($ruleObj, $ruleArgs))
    #if( $ruleObj )
    $ctx.decache($ruleObj)
    #end
    #set($ruleObj = $ctx.getObjectByName($spTools.class.forName("sailpoint.object.Rule"), "Rule-Server-Root-Path")) 
    #set($ruleArgs = {})
    #set($rootPath = $ctx.runRule($ruleObj, $ruleArgs))
    <![CDATA[<html>
    <head>
    <meta charset="UTF-8">	    
    #if($styleSheet)
    $styleSheet
    #end
    </head>
    <body>
    #if( $headerTemplate )
    $headerTemplate
    #end
    <br/>
    <p><strong>User's Information</strong></p><br/>
    
    #if($map.get("User's Name"))<strong>User's Name:</strong>$map.get("User's Name") <br/>#end
    #if($map.get("User's Network ID Provided By User (May be blank)"))<strong>User's Network ID Provided By User (May be blank):</strong>$map.get("User's Network ID Provided By User (May be blank)") <br/>#end
    #if($map.get("User's Email Address"))<strong>User's Email Address:</strong>$map.get("User's Email Address") <br/>#end
    #if($map.get("User's Type") )<strong>User's Type:</strong>$map.get("User's Type") <br/>#end
    #if($map.get("Job Title"))<strong>Job Title:</strong>$map.get("Job Title") <br/>#end
    #if($map.get("Department") )<strong>Department:</strong>$map.get("Department") <br/>#end
    #if($map.get("Location"))<strong>Location:</strong>$map.get("Location") <br/>#end
    #if($map.get("Employee Number"))<strong>Employee Number:</strong>$map.get("Employee Number") <br/>#end
     #if($map.get("Telephone Number"))<strong>Telephone Number:</strong>$map.get("Telephone Number") <br/>#end
    
    <br/><p><strong>Manager's Information</strong></p><br/>
    
    #if($map.get("Manager's Name"))<strong>Manager's Name:</strong>$map.get("Manager's Name") <br/>#end
    #if($map.get("Manager's Phone Number"))<strong>Manager's Phone Number:</strong>$map.get("Manager's Phone Number") <br/>#end
    #if($map.get("Manager's Department"))<strong>Manager's Department:</strong>$map.get("Manager's Department") <br/>#end
    #if($map.get("Manager's Email Address"))<strong>Manager's Email Address:</strong>$map.get("Manager's Email Address") <br/>#end
   
    
    <br/><p><strong>Submitter's Information</strong></p><br/>
    
    #if($map.get("Submitter's Name"))<strong>Submitter's Name:</strong>$map.get("Submitter's Name") <br/>#end
    #if($map.get("Submitter's Phone Number"))<strong>Submitter's Phone Number:</strong>$map.get("Submitter's Phone Number") <br/>#end
    #if($map.get("Submitter's Email Address"))<strong>Submitter's Email Address:</strong>$map.get("Submitter's Email Address") <br/>#end
   
    
    <br/><p><strong>Application Information</strong></p><br/>
    
    #if($map.get("Application Name"))<strong>Application Name:</strong>$map.get("Application Name") <br/>#end
    #if($map.get("Action"))<strong>Action:</strong>$map.get("Action") <br/>#end
    #if($map.get("ENTITLEMENTS"))<strong>ENTITLEMENTS:</strong>$map.get("ENTITLEMENTS") <br/>#end
    #if($map.get("Type of Access"))<strong>Type of Access:</strong>$map.get("Type of Access") <br/>#end
   #if($map.get("Provisioning Comments For Application"))<strong>Provisioning Comments For Application:</strong>$map.get("Provisioning Comments For Application") <br/>#end
    #if($map.get("Application Username Provided by Provisioning"))<strong>Application Username Provided by Provisioning:</strong>$map.get("Application Username Provided by Provisioning") <br/>#end
    #if($map.get("Requestor Comments For Application"))<strong>Requestor Comments For Application:</strong> $map.get("Requestor Comments For Application")<br/>#end
    #if($map.get("General Request Comments")) <strong>General Request Comments:</strong>$map.get("General Request Comments")<br/>#end
    
    <p>Thank you,<br/>
    The IAM Operations Team</p>
    #if( $footerTemplate )
    $footerTemplate
    #end
    </body>
    </html>]]>
  </Body>
  <Description>
    Email Template for notifying managers when an employee's account(s) are modified.
    Note that in addition to the declared arguments, all workflow variables,
    Step arguments, and Approval arguments defined in the Workflow are
    also available.
  </Description>
  <Signature>
    <Inputs>
      <Argument name="map" type="LinkedHashMap">
        <Description>The Workflow object being executed.</Description>
      </Argument>
      <Argument name="identityDisplayName" type="string">
        <Description>The display name of the Identity that is being changed.</Description>
      </Argument>
      <Argument name="subject" type="string">
        <Description>The display name of the Identity that is being changed.</Description>
      </Argument>
    </Inputs>
  </Signature>
  <Subject>SECURE- $!subject Access Request for USER $!identityDisplayName was processed</Subject>
</EmailTemplate>